grokcore.chameleon-4.0-py3.9-nspkg.pth
grokcore/chameleon/README.rst
grokcore/chameleon/__init__.py
grokcore/chameleon/components.py
grokcore/chameleon/configure.zcml
grokcore/chameleon/ftesting.zcml
grokcore/chameleon/tests/__init__.py
grokcore/chameleon/tests/templatefile.py
grokcore/chameleon/tests/test_megrok_chameleon.py
grokcore/chameleon/tests/cpt_fixture/__init__.py
grokcore/chameleon/tests/cpt_fixture/app.py
grokcore/chameleon/tests/cpt_fixture/app_templates/cavepainting.cpt
grokcore/chameleon/tests/cpt_fixture/app_templates/expressions.cpt
grokcore/chameleon/tests/cpt_fixture/app_templates/food.cpt
grokcore/chameleon/tests/cpt_fixture/app_templates/macromaster.cpt
grokcore/chameleon/tests/cpt_fixture/app_templates/macrouser.cpt
grokcore/chameleon/tests/cpt_fixture/app_templates/menu.cpt
grokcore/chameleon/tests/cpt_fixture/app_templates/namespace.cpt
grokcore/chameleon/tests/cpt_fixture/app_templates/vars.cpt
grokcore/chameleon/tests/cpt_fixture/static/test.css
grokcore/chameleon/tests/locale/de/LC_MESSAGES/grokcore-chameleon-tests.po
grokcore/chameleon/tests/locale/en/LC_MESSAGES/grokcore-chameleon-tests.po
grokcore/chameleon/tests/templates/foo.cpt
grokcore.chameleon-4.0.dist-info/LICENSE.txt
grokcore.chameleon-4.0.dist-info/METADATA
grokcore.chameleon-4.0.dist-info/WHEEL
grokcore.chameleon-4.0.dist-info/namespace_packages.txt
grokcore.chameleon-4.0.dist-info/top_level.txt
grokcore.chameleon-4.0.dist-info/RECORD
