Metadata-Version: 2.1
Name: grokcore.chameleon
Version: 4.0
Summary: Chameleon page template support for Grok
Home-page: https://pypi.org/project/grokcore.chameleon/
Author: Uli Fouquet
Author-email: zope-dev@zope.dev
License: ZPL
Keywords: grok chameleon template
Classifier: Environment :: Web Environment
Classifier: Intended Audience :: Developers
Classifier: License :: OSI Approved :: Zope Public License
Classifier: Programming Language :: Python
Classifier: Programming Language :: Python :: 3
Classifier: Programming Language :: Python :: 3.7
Classifier: Programming Language :: Python :: 3.8
Classifier: Programming Language :: Python :: 3.9
Classifier: Programming Language :: Python :: 3.10
Classifier: Programming Language :: Python :: 3.11
Classifier: Programming Language :: Python :: Implementation
Classifier: Programming Language :: Python :: Implementation :: CPython
Classifier: Programming Language :: Python :: Implementation :: PyPy
Classifier: Framework :: Zope :: 3
Requires-Python: >=3.7
License-File: LICENSE.txt
Requires-Dist: Chameleon (>=2.10)
Requires-Dist: grokcore.component
Requires-Dist: grokcore.view
Requires-Dist: setuptools
Requires-Dist: z3c.pt (>=2.2.2)
Requires-Dist: zope.i18n
Provides-Extra: test
Requires-Dist: grokcore.viewlet ; extra == 'test'
Requires-Dist: zope.app.appsetup ; extra == 'test'
Requires-Dist: zope.app.wsgi ; extra == 'test'
Requires-Dist: zope.testbrowser ; extra == 'test'
Requires-Dist: zope.testrunner ; extra == 'test'
